jcalapi/__init__.py
jcalapi/app.py
jcalapi/backend/__init__.py
jcalapi/backend/confluence.py
jcalapi/backend/exchange.py
jcalapi/backend/google.py
jcalapi/events.py
jcalapi/run.py
jcalapi/utils.py
jcalapi-0.1.9.dist-info/LICENSE
jcalapi-0.1.9.dist-info/METADATA
jcalapi-0.1.9.dist-info/WHEEL
jcalapi-0.1.9.dist-info/entry_points.txt
jcalapi-0.1.9.dist-info/RECORD
