Metadata-Version: 2.1
Name: jcalapi
Version: 0.1.9
Summary: Local calendar caching and JSON API
Home-page: https://github.com/pschmitt/jcalapi
License: GPL-3
Author: Philipp Schmitt
Author-email: philipp@schmitt.co
Requires-Python: >=3.10,<4.0
Classifier: License :: Other/Proprietary License
Classifier: Programming Language :: Python :: 3
Classifier: Programming Language :: Python :: 3.10
Classifier: Programming Language :: Python :: 3.11
Classifier: Programming Language :: Python :: 3.12
Classifier: Programming Language :: Python :: 3.13
Requires-Dist: asynccli (>=0.1.3,<0.2.0)
Requires-Dist: atlassian-python-api (>=3.38.0,<4.0.0)
Requires-Dist: beautifulsoup4 (>=4.12.2,<5.0.0)
Requires-Dist: diskcache (>=5.6.1,<6.0.0)
Requires-Dist: environs (>=9.5,<12.0)
Requires-Dist: exchangelib (>=5.0.3,<6.0.0)
Requires-Dist: fastapi (>=0.96,<0.116)
Requires-Dist: fastapi-utils (>=0.2.1,<0.8.0)
Requires-Dist: gcsa (>=2.2.0,<3.0.0)
Requires-Dist: httpx (>=0.24.1,<0.28.0)
Requires-Dist: icalendar (>=5.0.7,<7.0.0)
Requires-Dist: loguru (>=0.7.0,<0.8.0)
Requires-Dist: python-dateutil (>=2.8.2,<3.0.0)
Requires-Dist: python-multipart (>=0.0.6,<0.0.13)
Requires-Dist: recurring-ical-events (>=2.0.2,<4.0.0)
Requires-Dist: typing_inspect (>=0.9.0,<0.10.0)
Requires-Dist: uvicorn[standard] (>=0.22,<0.33)
Requires-Dist: xdg (>=6.0.0,<7.0.0)
